autorequests/__init__.py
autorequests/__main__.py
autorequests/commons.py
autorequests/parsing/__init__.py
autorequests/parsing/body.py
autorequests/parsing/fetch.py
autorequests/parsing/powershell.py
autorequests/request.py
autorequests/typings.py
autorequests-2.1.0.dist-info/entry_points.txt
autorequests-2.1.0.dist-info/LICENSE
autorequests-2.1.0.dist-info/METADATA
autorequests-2.1.0.dist-info/WHEEL
autorequests-2.1.0.dist-info/RECORD
